flaskfarm/__init__.py
flaskfarm/main.py
flaskfarm/cli/__init__.py
flaskfarm/cli/chage_ui.py
flaskfarm/cli/code_encode.py
flaskfarm/cli/encode.py
flaskfarm/files/config.yaml.template
flaskfarm/files/menu.yaml.template
flaskfarm/files/notify.yaml.template
flaskfarm/files/requirements_mini.txt
flaskfarm/files/requirements_normal.txt
flaskfarm/files/requirements_useful.txt
flaskfarm/lib/framework/__init__.py
flaskfarm/lib/framework/init_cache_manager.py
flaskfarm/lib/framework/init_declare.py
flaskfarm/lib/framework/init_main.py
flaskfarm/lib/framework/init_menu.py
flaskfarm/lib/framework/init_plugin.py
flaskfarm/lib/framework/init_route.py
flaskfarm/lib/framework/init_web.py
flaskfarm/lib/framework/log_viewer.py
flaskfarm/lib/framework/scheduler.py
flaskfarm/lib/framework/util.py
flaskfarm/lib/framework/version.py
flaskfarm/lib/framework/static/css/animate.min.css
flaskfarm/lib/framework/static/css/bootstrap.min.css
flaskfarm/lib/framework/static/css/custom.css
flaskfarm/lib/framework/static/css/showdown.css
flaskfarm/lib/framework/static/css/theme/Cerulean_bootstrap.min.css
flaskfarm/lib/framework/static/css/theme/Cosmo_bootstrap.min.css
flaskfarm/lib/framework/static/css/theme/Cyborg_bootstrap.min.css
flaskfarm/lib/framework/static/css/theme/Darkly_bootstrap.min.css
flaskfarm/lib/framework/static/css/theme/Default_bootstrap.min.css
flaskfarm/lib/framework/static/css/theme/Flatly_bootstrap.min.css
flaskfarm/lib/framework/static/css/theme/Journal_bootstrap.min.css
flaskfarm/lib/framework/static/css/theme/Litera_bootstrap.min.css
flaskfarm/lib/framework/static/css/theme/Lumen_bootstrap.min.css
flaskfarm/lib/framework/static/css/theme/Lux_bootstrap.min.css
flaskfarm/lib/framework/static/css/theme/Materia_bootstrap.min.css
flaskfarm/lib/framework/static/css/theme/Minty_bootstrap.min.css
flaskfarm/lib/framework/static/css/theme/Morph_bootstrap.min.css
flaskfarm/lib/framework/static/css/theme/Pulse_bootstrap.min.css
FlaskFarm-4.1.39.dist-info/METADATA
FlaskFarm-4.1.39.dist-info/WHEEL
FlaskFarm-4.1.39.dist-info/top_level.txt
FlaskFarm-4.1.39.dist-info/RECORD
