Metadata-Version: 2.1
Name: FlaskFarm
Version: 4.1.39
Summary: FlaskFarm
Home-page: https://github.com/flaskfarm/flaskfarm
Author: flaskfarm
Author-email: flaskfarm@gmail.com
Classifier: Programming Language :: Python :: 3
Classifier: License :: OSI Approved :: GNU General Public License (GPL)
Classifier: Operating System :: OS Independent
Requires-Python: >=3.9
Requires-Dist: Flask
Requires-Dist: Flask-SQLAlchemy
Requires-Dist: Flask-Login
Requires-Dist: Flask-Cors
Requires-Dist: Flask-SocketIO
Requires-Dist: python-engineio
Requires-Dist: python-socketio
Requires-Dist: Werkzeug
Requires-Dist: Jinja2
Requires-Dist: markupsafe
Requires-Dist: itsdangerous
Requires-Dist: apscheduler
Requires-Dist: pytz
Requires-Dist: requests
Requires-Dist: discord-webhook
Requires-Dist: pyyaml
Requires-Dist: telepot-mod
Requires-Dist: Flask-Dropzone
Requires-Dist: psutil
Requires-Dist: pillow
Requires-Dist: gevent
Requires-Dist: gevent-websocket
Requires-Dist: pycryptodome
Requires-Dist: json-fix
